{"trial_id": "0019", "hyperparameters": {"space": [{"class_name": "Choice", "config": {"name": "activation", "default": "relu", "conditions": [], "values": ["relu", "tanh"], "ordered": false}}, {"class_name": "Int", "config": {"name": "layer_1", "default": null, "conditions": [], "min_value": 1, "max_value": 1000, "step": 100, "sampling": null}}, {"class_name": "Int", "config": {"name": "layer_2", "default": null, "conditions": [], "min_value": 1, "max_value": 1000, "step": 100, "sampling": null}}, {"class_name": "Choice", "config": {"name": "learning_rate", "default": 0.01, "conditions": [], "values": [0.01, 0.001, 0.0001], "ordered": true}}], "values": {"activation": "relu", "layer_1": 901, "layer_2": 601, "learning_rate": 0.0001, "tuner/epochs": 4, "tuner/initial_epoch": 0, "tuner/bracket": 1, "tuner/round": 0}}, "metrics": {"metrics": {"loss": {"direction": "min", "observations": [{"value": [0.2443608045578003], "step": 3}]}, "accuracy": {"direction": "max", "observations": [{"value": [0.976937472820282], "step": 3}]}, "val_loss": {"direction": "min", "observations": [{"value": [0.6885554790496826], "step": 3}]}, "val_accuracy": {"direction": "max", "observations": [{"value": [0.9590833187103271], "step": 3}]}}}, "score": 0.9590833187103271, "best_step": 3, "status": "COMPLETED"}